aircopy/__init__.py
aircopy/_version.py
aircopy/autogen.py
aircopy/cli.py
aircopy/database.py
aircopy/datatype.py
aircopy/io.py
aircopy/parser.py
aircopy/tools.py
aircopy/tests/__init__.py
aircopy/tests/conftest.py
aircopy/tests/test_autogen.py
aircopy/tests/test_cli.py
aircopy/tests/test_database.py
aircopy/tests/test_examples.py
aircopy/tests/test_io.py
aircopy/tests/test_parser.py
aircopy/tests/test_tools.py
aircopy-0.0.2.dist-info/AUTHORS.rst
aircopy-0.0.2.dist-info/LICENSE
aircopy-0.0.2.dist-info/METADATA
aircopy-0.0.2.dist-info/WHEEL
aircopy-0.0.2.dist-info/entry_points.txt
aircopy-0.0.2.dist-info/top_level.txt
aircopy-0.0.2.dist-info/RECORD
