Metadata-Version: 2.1
Name: aircopy
Version: 0.0.2
Summary: The CLI software to copy airtable data to Billinge group database
Home-page: https://github.com/st3107/aircopy
Author: Songsheng Tao
Author-email: st3107@columbia.edu
License: BSD (3-clause)
Platform: UNKNOWN
Classifier: Development Status :: 2 - Pre-Alpha
Classifier: Natural Language :: English
Classifier: Programming Language :: Python :: 3
Requires-Python: >=3.7
Requires-Dist: airtable-python-wrapper
Requires-Dist: ruamel.yaml
Requires-Dist: nameparser
Requires-Dist: fire
